LockonTools/EmlReader.py
LockonTools/Tools.py
LockonTools/TradeCalender.py
LockonTools/__init__.py
LockonTools/package_param.py
LockonTools-0.0.6.dist-info/LICENSE
LockonTools-0.0.6.dist-info/METADATA
LockonTools-0.0.6.dist-info/WHEEL
LockonTools-0.0.6.dist-info/top_level.txt
LockonTools-0.0.6.dist-info/RECORD
